Metadata-Version: 2.1
Name: warplol
Version: 1.3.0
Summary: Short URLs using the warp.lol APIs.
Home-page: https://warp.lol/
Author: Filippo Romani
Author-email: mail@filipporomani.it
License: UNKNOWN
Platform: UNKNOWN
Classifier: Programming Language :: Python :: 3
Classifier: Programming Language :: Python :: 3.7
Classifier: Programming Language :: Python :: 3.8
Classifier: Programming Language :: Python :: 3.9
Classifier: Programming Language :: Python :: 3.10
Classifier: Topic :: Software Development :: Libraries :: Python Modules
Classifier: Development Status :: 4 - Beta
Classifier: Operating System :: OS Independent
Requires-Python: >=3
License-File: LICENSE
